{"Year":[2016,2019,2021,2022,2025,2016,2019,2021,2022,2025,2016,2019,2021,2022,2025],"OBS_STATUS":["A","A","A","A","A","A","A","A","A","A","A","A","A","A","A"],"UNIT_MULT":["0","0","0","0","0","0","0","0","0","0","0","0","0","0","0"],"SOURCE_DETAIL":["MICS 2021/22, CSO","MICS 2021/22, CSO","MICS 2021/22, CSO","MICS 2021/22, CSO","MICS 2021/22, CSO","MICS 2021/22, CSO","MICS 2021/22, CSO","MICS 2021/22, CSO","MICS 2021/22, CSO","MICS 2021/22, CSO","MICS 2021/22, CSO","MICS 2021/22, CSO","MICS 2021/22, CSO","MICS 2021/22, CSO","MICS 2021/22, CSO"],"SERIES":["SH_SAN_SAFE","SH_SAN_SAFE","SH_SAN_SAFE","SH_SAN_SAFE","SH_SAN_SAFE","SH_SAN_SAFE","SH_SAN_SAFE","SH_SAN_SAFE","SH_SAN_SAFE","SH_SAN_SAFE","SH_SAN_SAFE","SH_SAN_SAFE","SH_SAN_SAFE","SH_SAN_SAFE","SH_SAN_SAFE"],"REF_AREA":["748","748","748","748","748","748","748","748","748","748","748","748","748","748","748"],"URBANISATION":[null,null,null,null,null,"R","R","R","R","R","U","U","U","U","U"],"UNIT_MEASURE":["PT","PT","PT","PT","PT","PT","PT","PT","PT","PT","PT","PT","PT","PT","PT"],"Value":[53.0,53.0,46.0,46.0,59.4,55.0,55.0,47.8,47.8,62.8,47.5,47.5,42.3,42.3,49.0]}